pyrepohistory/__init__.py
pyrepohistory/main.py
pyrepohistory/lib/__init__.py
pyrepohistory/lib/cloning.py
pyrepohistory/lib/commit_analysis.py
pyrepohistory/lib/primary_language.py
pyrepohistory-0.0.11.dist-info/LICENSE
pyrepohistory-0.0.11.dist-info/METADATA
pyrepohistory-0.0.11.dist-info/WHEEL
pyrepohistory-0.0.11.dist-info/top_level.txt
pyrepohistory-0.0.11.dist-info/RECORD
