Metadata-Version: 2.1
Name: pyrepohistory
Version: 0.0.11
Author: Matt Gaughan
License-File: LICENSE
